bioacoustics_model_zoo/__init__.py
bioacoustics_model_zoo/appdirs.py
bioacoustics_model_zoo/birdnet.py
bioacoustics_model_zoo/birdnet_without_tf.ipynb
bioacoustics_model_zoo/bmz_birdset/birdset_preprocessing.py
bioacoustics_model_zoo/bmz_birdset/bmz_birdset_convnext.py
bioacoustics_model_zoo/bmz_birdset/bmz_birdset_efficientnetB1.py
bioacoustics_model_zoo/bmz_birdset/configs/callbacks/cluster.yaml
bioacoustics_model_zoo/bmz_birdset/configs/callbacks/default.yaml
bioacoustics_model_zoo/bmz_birdset/configs/callbacks/early_stopping.yaml
bioacoustics_model_zoo/bmz_birdset/configs/callbacks/learning_rate_monitor.yaml
bioacoustics_model_zoo/bmz_birdset/configs/callbacks/model_checkpoint.yaml
bioacoustics_model_zoo/bmz_birdset/configs/callbacks/model_summary.yaml
bioacoustics_model_zoo/bmz_birdset/configs/callbacks/progress_bar.yaml
bioacoustics_model_zoo/bmz_birdset/configs/callbacks/rich_progress_bar.yaml
bioacoustics_model_zoo/bmz_birdset/configs/callbacks/time_tracking.yaml
bioacoustics_model_zoo/bmz_birdset/configs/datamodule/HSN.yaml
bioacoustics_model_zoo/bmz_birdset/configs/datamodule/NBP.yaml
bioacoustics_model_zoo/bmz_birdset/configs/datamodule/NES.yaml
bioacoustics_model_zoo/bmz_birdset/configs/datamodule/PER.yaml
bioacoustics_model_zoo/bmz_birdset/configs/datamodule/POW.yaml
bioacoustics_model_zoo/bmz_birdset/configs/datamodule/SNE.yaml
bioacoustics_model_zoo/bmz_birdset/configs/datamodule/SSW.yaml
bioacoustics_model_zoo/bmz_birdset/configs/datamodule/UHH.yaml
bioacoustics_model_zoo/bmz_birdset/configs/datamodule/XCL.yaml
bioacoustics_model_zoo/bmz_birdset/configs/datamodule/XCM.yaml
bioacoustics_model_zoo/bmz_birdset/configs/datamodule/esc50.yaml
bioacoustics_model_zoo/bmz_birdset/configs/datamodule/inference/HSN_inf.yaml
bioacoustics_model_zoo/bmz_birdset/configs/datamodule/inference/NBP_inf.yaml
bioacoustics_model_zoo/bmz_birdset/configs/datamodule/inference/NES_inf.yaml
bioacoustics_model_zoo/bmz_birdset/configs/datamodule/inference/PER_inf.yaml
bioacoustics_model_zoo-0.12.0.dist-info/LICENSE
bioacoustics_model_zoo-0.12.0.dist-info/METADATA
bioacoustics_model_zoo-0.12.0.dist-info/WHEEL
bioacoustics_model_zoo-0.12.0.dist-info/RECORD
