Metadata-Version: 2.3
Name: bioacoustics-model-zoo
Version: 0.12.0
Summary: Public repository of machine learning models for bioacoustics, with OpenSoundscape integration
License: MIT
Keywords: bioacoustics,machine-learning,audio,ecology,birds,sound-classification,deep-learning
Author: sammlapp
Author-email: sammlapp@gmail.com
Requires-Python: >=3.9,<4.0
Classifier: Development Status :: 4 - Beta
Classifier: Intended Audience :: Science/Research
Classifier: License :: OSI Approved :: MIT License
Classifier: Operating System :: OS Independent
Classifier: Programming Language :: Python :: 3
Classifier: Programming Language :: Python :: 3.9
Classifier: Programming Language :: Python :: 3.10
Classifier: Programming Language :: Python :: 3.11
Classifier: Programming Language :: Python :: 3.12
Classifier: Programming Language :: Python :: 3.13
Classifier: Topic :: Multimedia :: Sound/Audio :: Analysis
Classifier: Topic :: Scientific/Engineering :: Artificial Intelligence
Classifier: Topic :: Scientific/Engineering :: Bio-Informatics
Provides-Extra: all
Provides-Extra: birdnet
Provides-Extra: birdset
Provides-Extra: hawkears
Provides-Extra: pytorch
Provides-Extra: tensorflow
Requires-Dist: PyGithub (>=2.6.1)
Requires-Dist: ai-edge-litert (>=1.0.0,<1.4) ; extra == "birdnet" or extra == "all"
Requires-Dist: opensoundscape (>=0.11.2)
Requires-Dist: tensorflow (>=2.13.0) ; extra == "tensorflow" or extra == "all"
Requires-Dist: tensorflow-hub (>=0.14.0) ; extra == "tensorflow" or extra == "all"
Requires-Dist: timm (>=0.9.0) ; extra == "hawkears" or extra == "all"
Requires-Dist: torch (>=1.13.0) ; extra == "hawkears" or extra == "birdset" or extra == "pytorch" or extra == "all"
Requires-Dist: torchaudio (>=0.13.0) ; extra == "hawkears" or extra == "birdset" or extra == "pytorch" or extra == "all"
Requires-Dist: torchvision (>=0.14.0) ; extra == "hawkears" or extra == "birdset" or extra == "pytorch" or extra == "all"
Requires-Dist: transformers (>=4.20.0) ; extra == "birdset" or extra == "all"
Project-URL: Documentation, https://github.com/kitzeslab/bioacoustics-model-zoo/blob/main/README.md
Project-URL: Homepage, https://github.com/kitzeslab/bioacoustics-model-zoo
Project-URL: Repository, https://github.com/kitzeslab/bioacoustics-model-zoo
